{
  "id": "65ace7824cf93c000184bca4",
  "name": "Content Creation",
  "slug": "content-creation",
  "description": null,
  "feature_image": "https://tokenwisdom.ghost.io/content/images/2024/01/-Resonate-B2B-ebooks-7-1.gif",
  "visibility": "public",
  "meta_title": null,
  "meta_description": null,
  "og_image": null,
  "og_title": null,
  "og_description": null,
  "twitter_image": null,
  "twitter_title": null,
  "twitter_description": null,
  "codeinjection_head": null,
  "codeinjection_foot": null,
  "canonical_url": null,
  "accent_color": null,
  "url": "https://tokenwisdom.ghost.io/tag/content-creation/",
  "posts": [
    {
      "id": "68858ddc845b5c0001afdffa",
      "title": "Scrapyard Futures in the Digital Ruins",
      "slug": "scrapyard-futures-in-the-digital-ruins",
      "published_at": "2025-07-24T09:20:00.000-07:00",
      "url": "https://tokenwisdom.ghost.io/scrapyard-futures-in-the-digital-ruins/",
      "featured": false,
      "reading_time": 9
    },
    {
      "id": "685ba5b2ed1d9d0001db189e",
      "title": "The Misinformation Industrial Complex",
      "slug": "the-misinformation-industrial-complex",
      "published_at": "2025-06-26T18:28:33.000-07:00",
      "url": "https://tokenwisdom.ghost.io/the-misinformation-industrial-complex/",
      "featured": false,
      "reading_time": 11
    },
    {
      "id": "67424d2d7cd669000121393e",
      "title": "The Power of Questioning: Revolutionizing Learning in the AI Era",
      "slug": "the-power-of-questioning-revolutionizing-learning-in-the-ai-era",
      "published_at": "2024-09-26T14:05:00.000-07:00",
      "url": "https://tokenwisdom.ghost.io/the-power-of-questioning-revolutionizing-learning-in-the-ai-era/",
      "featured": false,
      "reading_time": 11
    },
    {
      "id": "6742453b7cd66900012138dd",
      "title": "The Audio Revolution: AI and the Future of Sound",
      "slug": "the-audio-revolution-ai-and-the-future-of-sound",
      "published_at": "2024-09-19T13:25:00.000-07:00",
      "url": "https://tokenwisdom.ghost.io/the-audio-revolution-ai-and-the-future-of-sound/",
      "featured": false,
      "reading_time": 7
    },
    {
      "id": "660adb03945b2e000170f06d",
      "title": "Disney’s Autonomatronics Odyssey",
      "slug": "disneys-autonomatronics-odyssey",
      "published_at": "2024-04-01T23:11:00.000-07:00",
      "url": "https://tokenwisdom.ghost.io/disneys-autonomatronics-odyssey/",
      "featured": false,
      "reading_time": 22
    },
    {
      "id": "65fa3184b29fd300012f676b",
      "title": "I'm an ElevenLabs Pro!",
      "slug": "im-an-elevenlabs-pro",
      "published_at": "2024-03-20T13:41:12.000-07:00",
      "url": "https://tokenwisdom.ghost.io/im-an-elevenlabs-pro/",
      "featured": false,
      "reading_time": 11
    },
    {
      "id": "65ab51bb4cf93c000184b745",
      "title": "Dear @Medium, What Are You Doing?",
      "slug": "dear-medium-what-are-you-doing",
      "published_at": "2013-05-15T12:24:02.000-07:00",
      "url": "https://tokenwisdom.ghost.io/dear-medium-what-are-you-doing/",
      "featured": false,
      "reading_time": 3
    }
  ],
  "post_count": 7,
  "local_feature_image": "content-creation_feature__-Resonate-B2B-ebooks-7-1.gif"
}