{
  "id": "65d3905695b6a90001731264",
  "name": "#unlisted",
  "slug": "hash-unlisted",
  "description": null,
  "feature_image": null,
  "visibility": "internal",
  "meta_title": null,
  "meta_description": null,
  "og_image": null,
  "og_title": null,
  "og_description": null,
  "twitter_image": null,
  "twitter_title": null,
  "twitter_description": null,
  "codeinjection_head": null,
  "codeinjection_foot": null,
  "canonical_url": null,
  "accent_color": null,
  "url": "https://tokenwisdom.ghost.io/404/",
  "posts": [
    {
      "id": "65f73d79ed6d88000174d2ac",
      "title": "The Transformative Power of Generalists in a Specialized World",
      "slug": "the-transformative-power-of-generalists-in-a-specialized-world",
      "published_at": "2024-03-17T12:22:29.000-07:00",
      "url": "https://tokenwisdom.ghost.io/featured/the-transformative-power-of-generalists-in-a-specialized-world/",
      "featured": true,
      "reading_time": 23
    },
    {
      "id": "65f6733aed6d88000174d0e6",
      "title": "A Comprehensive Exploration of NeRF and Gaussian Splatting",
      "slug": "a-comprehensive-exploration-of-nerf-and-gaussian-splatting",
      "published_at": "2024-03-11T01:08:00.000-07:00",
      "url": "https://tokenwisdom.ghost.io/a-comprehensive-exploration-of-nerf-and-gaussian-splatting/",
      "featured": false,
      "reading_time": 11
    },
    {
      "id": "65d4929f692af4000194452c",
      "title": "Navigating the Consequences of Intellectual Property Law",
      "slug": "navigating-the-consequences-of-intellectual-property-law",
      "published_at": "2024-02-18T17:40:00.000-08:00",
      "url": "https://tokenwisdom.ghost.io/navigating-the-consequences-of-intellectual-property-law/",
      "featured": false,
      "reading_time": 16
    },
    {
      "id": "65c11a1c470b1400012b7a81",
      "title": "The Lone Star State Transforms into a Tech Powerhouse",
      "slug": "texas-an-american-chipmaking-oasis",
      "published_at": "2024-02-04T11:37:00.000-08:00",
      "url": "https://tokenwisdom.ghost.io/texas-an-american-chipmaking-oasis/",
      "featured": false,
      "reading_time": 12
    },
    {
      "id": "65a9b75cebf14f0001f3bdf4",
      "title": "Revolutionizing Education: When Silicon Meets Chalk",
      "slug": "revolutionizing-education-the-impact-of-artificial-intelligence",
      "published_at": "2023-10-23T16:50:00.000-07:00",
      "url": "https://tokenwisdom.ghost.io/featured/revolutionizing-education-the-impact-of-artificial-intelligence/",
      "featured": true,
      "reading_time": 11
    },
    {
      "id": "65a9c53bebf14f0001f3be81",
      "title": "France’s Mistral AI: Stepping into the Arena",
      "slug": "frances-mistral-ai-stepping-into-the-arena-to-challenge-the-giants",
      "published_at": "2023-09-30T17:45:00.000-07:00",
      "url": "https://tokenwisdom.ghost.io/featured/frances-mistral-ai-stepping-into-the-arena-to-challenge-the-giants/",
      "featured": true,
      "reading_time": 10
    },
    {
      "id": "65aa1cfcebf14f0001f3c08a",
      "title": "Unmasking Biases in Pre-Trained Transformers with Laundered Data",
      "slug": "laundered-data",
      "published_at": "2023-07-07T00:32:00.000-07:00",
      "url": "https://tokenwisdom.ghost.io/featured/laundered-data/",
      "featured": true,
      "reading_time": 9
    },
    {
      "id": "65aa1327ebf14f0001f3c061",
      "title": "The Path to Artificial General Intelligence",
      "slug": "the-path-to-artificial-general-intelligence",
      "published_at": "2023-05-18T23:17:00.000-07:00",
      "url": "https://tokenwisdom.ghost.io/featured/the-path-to-artificial-general-intelligence/",
      "featured": true,
      "reading_time": 5
    },
    {
      "id": "65a9c298ebf14f0001f3be58",
      "title": "The Rise of Algorithms: Are They Taking Over?",
      "slug": "the-rise-of-algorithms-are-they-taking-over",
      "published_at": "2023-05-10T17:34:00.000-07:00",
      "url": "https://tokenwisdom.ghost.io/featured/the-rise-of-algorithms-are-they-taking-over/",
      "featured": true,
      "reading_time": 7
    },
    {
      "id": "65a9c3dfebf14f0001f3be6c",
      "title": "The Era of Explainable AI In Today's World: The Future, The Insights, and The Trust",
      "slug": "the-era-of-explainable-ai-in-todays-world",
      "published_at": "2023-04-11T17:40:00.000-07:00",
      "url": "https://tokenwisdom.ghost.io/featured/the-era-of-explainable-ai-in-todays-world/",
      "featured": true,
      "reading_time": 6
    },
    {
      "id": "65a9f117ebf14f0001f3bf92",
      "title": "The Rise of Bitcoin Ordinals: Why They Matter",
      "slug": "the-rise-of-bitcoin-ordinals-why-they-matter",
      "published_at": "2023-02-16T19:51:00.000-08:00",
      "url": "https://tokenwisdom.ghost.io/featured/the-rise-of-bitcoin-ordinals-why-they-matter/",
      "featured": true,
      "reading_time": 5
    },
    {
      "id": "65ab51bb4cf93c000184b73a",
      "title": "LinkedIn, Isn’t Good Enough",
      "slug": "linkedin-isnt-good-enough",
      "published_at": "2014-05-27T15:55:07.000-07:00",
      "url": "https://tokenwisdom.ghost.io/featured/linkedin-isnt-good-enough/",
      "featured": true,
      "reading_time": 5
    },
    {
      "id": "65a9c7b7ebf14f0001f3bebb",
      "title": "You Can Sell Your Time, But You Can Never Buy It Back",
      "slug": "you-can-sell-your-time-but-you-can-never-buy-it-back",
      "published_at": "2013-06-22T17:00:00.000-07:00",
      "url": "https://tokenwisdom.ghost.io/featured/you-can-sell-your-time-but-you-can-never-buy-it-back/",
      "featured": true,
      "reading_time": 4
    },
    {
      "id": "65a9e70aebf14f0001f3bf1f",
      "title": "The Cult(ure) of Innovation",
      "slug": "the-cult-ure-of-innovation",
      "published_at": "2013-05-15T16:00:00.000-07:00",
      "url": "https://tokenwisdom.ghost.io/featured/the-cult-ure-of-innovation/",
      "featured": true,
      "reading_time": 5
    },
    {
      "id": "65ab51bb4cf93c000184b74f",
      "title": "The Art of Confidence",
      "slug": "the-art-of-confidence",
      "published_at": "2013-05-12T09:58:45.000-07:00",
      "url": "https://tokenwisdom.ghost.io/featured/the-art-of-confidence/",
      "featured": true,
      "reading_time": 6
    },
    {
      "id": "65ab51bb4cf93c000184b752",
      "title": "The Five Things That Will Get You Nowhere Fast",
      "slug": "the-five-things-that-will-get-you-nowhere-fast",
      "published_at": "2013-05-06T20:09:20.000-07:00",
      "url": "https://tokenwisdom.ghost.io/featured/the-five-things-that-will-get-you-nowhere-fast/",
      "featured": true,
      "reading_time": 1
    },
    {
      "id": "65fd1f665d866c000116398a",
      "title": "Without The Knowledge, What Do You Have?",
      "slug": "the-knowledge",
      "published_at": "2013-03-21T00:00:00.000-07:00",
      "url": "https://tokenwisdom.ghost.io/the-knowledge/",
      "featured": false,
      "reading_time": 1
    }
  ],
  "post_count": 17,
  "local_feature_image": null
}